weppy_REST-0.4.2.dist-info/DESCRIPTION.rst
weppy_REST-0.4.2.dist-info/METADATA
weppy_REST-0.4.2.dist-info/RECORD
weppy_REST-0.4.2.dist-info/WHEEL
weppy_REST-0.4.2.dist-info/metadata.json
weppy_REST-0.4.2.dist-info/top_level.txt
weppy_rest/__init__.py
weppy_rest/appmodule.py
weppy_rest/ext.py
weppy_rest/helpers.py
weppy_rest/parsers.py
weppy_rest/serializers.py
