Metadata-Version: 2.0
Name: weppy-REST
Version: 0.4.2
Summary: REST extension for weppy framework
Home-page: https://github.com/gi0baro/weppy-rest
Author: Giovanni Barillari
Author-email: gi0baro@d4net.org
License: BSD
Platform: any
Classifier: Development Status :: 4 - Beta
Classifier: Environment :: Web Environment
Classifier: Intended Audience :: Developers
Classifier: License :: OSI Approved :: BSD License
Classifier: Operating System :: OS Independent
Classifier: Programming Language :: Python
Classifier: Programming Language :: Python :: 2
Classifier: Programming Language :: Python :: 3
Classifier: Topic :: Internet :: WWW/HTTP :: Dynamic Content
Classifier: Topic :: Software Development :: Libraries :: Python Modules
Classifier: Topic :: Text Processing :: Markup :: HTML
Requires-Dist: weppy (>=1.0)
